fastapi_oauth_client/__init__.py
fastapi_oauth_client/endpoints.py
fastapi_oauth_client/settings.py
fastapi_oauth_client/verify_token.py
fastapi_oauth_client/resources/__init__.py
fastapi_oauth_client/resources/success_template.py
tests/__init__.py
tests/conftest.py
tests/test_endpoints.py
tests/test_settings.py
tests/test_token_verification.py
fastapi_oauth_client-1.0.1.dist-info/LICENSE
fastapi_oauth_client-1.0.1.dist-info/METADATA
fastapi_oauth_client-1.0.1.dist-info/WHEEL
fastapi_oauth_client-1.0.1.dist-info/top_level.txt
fastapi_oauth_client-1.0.1.dist-info/RECORD
