Metadata-Version: 2.1
Name: fastapi-oauth-client
Version: 1.0.1
Summary: FastAPI Authorization Framework
Home-page: http://pypi.python.org/projects/xxxx
Author: Schroeck IT-Consulting GbR
Author-email: hello@schroeck-consulting.de
License: GPL
Classifier: Programming Language :: Python
Classifier: Programming Language :: Python :: 3.9
Classifier: Programming Language :: Python :: 3.10
Classifier: Topic :: Software Development :: Libraries :: Python Modules
License-File: LICENSE
Requires-Dist: fastapi
Requires-Dist: requests
Requires-Dist: pandas
Requires-Dist: uvicorn
Requires-Dist: pyjwt[crypto]
Requires-Dist: itsdangerous
Requires-Dist: httpx
Requires-Dist: authlib
